ohlc_toolkit/__init__.py
ohlc_toolkit/bitstamp_dataset_downloader.py
ohlc_toolkit/config/__init__.py
ohlc_toolkit/config/logging.py
ohlc_toolkit/csv_reader.py
ohlc_toolkit/exceptions/__init__.py
ohlc_toolkit/future_returns/__init__.py
ohlc_toolkit/future_returns/percentage_return.py
ohlc_toolkit/pandas_ta/__init__.py
ohlc_toolkit/pandas_ta/percent_return.py
ohlc_toolkit/pandas_ta/utils.py
ohlc_toolkit/timeframes.py
ohlc_toolkit/transform.py
ohlc_toolkit/utils.py
ohlc_toolkit-0.4.0.dist-info/LICENSE
ohlc_toolkit-0.4.0.dist-info/METADATA
ohlc_toolkit-0.4.0.dist-info/WHEEL
ohlc_toolkit-0.4.0.dist-info/RECORD
