Metadata-Version: 2.3
Name: ohlc-toolkit
Version: 0.4.0
Summary: A flexible toolkit for working with OHLC data and generating custom timeframes from minute data.
License: MIT
Keywords: ohlc,price,candlestick,financial,market-data,time-series
Author: Mourits de Beer
Author-email: ff137@proton.me
Requires-Python: >=3.10,<4.0
Classifier: License :: OSI Approved :: MIT License
Classifier: Programming Language :: Python :: 3
Classifier: Programming Language :: Python :: 3.10
Classifier: Programming Language :: Python :: 3.11
Classifier: Programming Language :: Python :: 3.12
Classifier: Programming Language :: Python :: 3.13
Requires-Dist: loguru (>=0.7.3)
Requires-Dist: orjson (>=3.10.15,<4.0.0)
Requires-Dist: pandas (>=2.3.0,<3.0.0)
Requires-Dist: requests (>=2.32.3,<3.0.0)
Requires-Dist: tqdm (>=4.66.4,<5.0.0)
Project-URL: Repository, https://github.com/ff137/ohlc-toolkit
